python_active_versions/__init__.py
python_active_versions/bundle.py
python_active_versions/cli_tools/__init__.py
python_active_versions/cli_tools/cli.py
python_active_versions/py.typed
python_active_versions/py.typed.license
python_active_versions/python_active_versions.py
python_active_versions/utility.py
python_active_versions-1.19.0.dist-info/AUTHORS.rst
python_active_versions-1.19.0.dist-info/AUTHORS.rst.license
python_active_versions-1.19.0.dist-info/LICENSES/MIT.txt
python_active_versions-1.19.0.dist-info/METADATA
python_active_versions-1.19.0.dist-info/WHEEL
python_active_versions-1.19.0.dist-info/entry_points.txt
python_active_versions-1.19.0.dist-info/RECORD
