Metadata-Version: 2.1
Name: python-active-versions
Version: 1.19.0
Summary: Gather active python versions.
Home-page: https://github.com/gpongelli/python-active-versions
License: MIT
Author: Gabriele Pongelli
Author-email: gpongelli@users.noreply.github.com
Requires-Python: >=3.8.0,<3.13
Classifier: Development Status :: 5 - Production/Stable
Classifier: Intended Audience :: Developers
Classifier: License :: OSI Approved :: MIT License
Classifier: Natural Language :: English
Classifier: Programming Language :: Python :: 3
Classifier: Programming Language :: Python :: 3.8
Classifier: Programming Language :: Python :: 3.9
Classifier: Programming Language :: Python :: 3.10
Classifier: Programming Language :: Python :: 3.11
Classifier: Programming Language :: Python :: 3.12
Requires-Dist: beautifulsoup4 (>=4.12.0,<5.0.0)
Requires-Dist: click (>=8.1.7,<9.0.0)
Requires-Dist: cloup (>=3.0.0,<4.0.0)
Requires-Dist: lxml_html_clean (>=0.1.1,<0.2.0)
Requires-Dist: requests (>=2.32.0,<3.0.0)
Requires-Dist: requests-cache (>=1.2.1,<2.0.0)
Requires-Dist: requests-html (>=0.10.0,<0.11.0)
Project-URL: Changelog, https://gpongelli.github.io/python-active-versions/history.html
Project-URL: Documentation, https://gpongelli.github.io/python-active-versions/
Project-URL: Issue Tracker, https://github.com/gpongelli/python-active-versions/issues
Project-URL: Repository, https://github.com/gpongelli/python-active-versions
Project-URL: Source, https://github.com/gpongelli/python-active-versions
